statemachine_decorator/__init__.py
statemachine_decorator/exceptions.py
statemachine_decorator/statemachine.py
statemachine_decorator-2.0.2.dist-info/METADATA
statemachine_decorator-2.0.2.dist-info/WHEEL
statemachine_decorator-2.0.2.dist-info/licenses/LICENSE
statemachine_decorator-2.0.2.dist-info/RECORD
