Metadata-Version: 2.1
Name: statemachine_decorator
Version: 2.0.2
Summary: This package offers a function which decorate any class with given states. And make sure any its object's state switch between them.
Project-URL: Homepage, https://github.com/chtheitmmmmm/statemachine
Project-URL: Bug Tracker, https://github.com/chtheitmmmmm/statemachine/issues
Author-email: Cmtheit <cmtheit@outlook.com>
License-File: LICENSE
Classifier: License :: OSI Approved :: MIT License
Classifier: Operating System :: OS Independent
Classifier: Programming Language :: Python :: 3
Requires-Python: >=3.8
